nova/__init__.py
nova/__main__.py
nova/assets/spa.js
nova/internal/__init__.py
nova/internal/building.py
nova/internal/interface.py
nova/internal/stack.py
nova/plugins/__init__.py
nova/plugins/plugin_minify.py
nova/plugins/plugin_nonce.py
nova/plugins/plugin_sass.py
nova/plugins/plugin_spa.py
nova/plugins/plugin_static.py
nova/plugins/plugin_typescript.py
nova/plugins/binaries/__init__.py
nova_framework-0.14.dist-info/METADATA
nova_framework-0.14.dist-info/WHEEL
nova_framework-0.14.dist-info/entry_points.txt
nova_framework-0.14.dist-info/licenses/LICENSE.txt
nova_framework-0.14.dist-info/RECORD
