Metadata-Version: 2.4
Name: nova-framework
Version: 0.14
Summary: A site building framework for people who like to keep it simple.
Project-URL: Documentation, https://github.com/iiPythonx/nova#readme
Project-URL: Issues, https://github.com/iiPythonx/nova/issues
Project-URL: Source, https://github.com/iiPythonx/nova
Author-email: iiPython <ben@iipython.dev>
License-Expression: MIT
License-File: LICENSE.txt
Classifier: Development Status :: 4 - Beta
Classifier: Programming Language :: Python
Classifier: Programming Language :: Python :: 3.11
Classifier: Programming Language :: Python :: 3.12
Classifier: Programming Language :: Python :: 3.13
Classifier: Programming Language :: Python :: Implementation :: CPython
Requires-Python: >=3.11
Requires-Dist: click>=8.1.7
Requires-Dist: jinja2>=3.1.4
Requires-Dist: rich>=13.9.4
Requires-Dist: watchfiles>=0.22.0
Requires-Dist: websockets>=14.2
